traceguide/__init__.py
traceguide/connection.py
traceguide/constants.py
traceguide/instrument.py
traceguide/util.py
traceguide/version.py
traceguide/crouton/__init__.py
traceguide/crouton/constants.py
traceguide/crouton/ReportingService.py
traceguide/crouton/ttypes.py
traceguide-1.0.28.dist-info/DESCRIPTION.rst
traceguide-1.0.28.dist-info/METADATA
traceguide-1.0.28.dist-info/metadata.json
traceguide-1.0.28.dist-info/RECORD
traceguide-1.0.28.dist-info/top_level.txt
traceguide-1.0.28.dist-info/WHEEL
