Metadata-Version: 2.0
Name: traceguide
Version: 1.0.28
Summary: Official Traceguide Library for Python
Home-page: UNKNOWN
Author: Resonance Labs, Inc.
Author-email: UNKNOWN
License: UNKNOWN
Keywords: traceguide
Platform: UNKNOWN
Classifier: Operating System :: OS Independent
Classifier: Programming Language :: Python :: 2
Requires-Dist: thrift (==0.9.2)
Requires-Dist: jsonpickle
